gemseo_calibration/__init__.py
gemseo_calibration/calibrator.py
gemseo_calibration/post_processor.py
gemseo_calibration/scenario.py
gemseo_calibration/metrics/__init__.py
gemseo_calibration/metrics/base_calibration_metric.py
gemseo_calibration/metrics/base_integrated_metric.py
gemseo_calibration/metrics/base_mean_metric.py
gemseo_calibration/metrics/factory.py
gemseo_calibration/metrics/iae.py
gemseo_calibration/metrics/ise.py
gemseo_calibration/metrics/mae.py
gemseo_calibration/metrics/mse.py
gemseo_calibration/metrics/settings.py
gemseo_calibration/post/__init__.py
gemseo_calibration/post/_matplotlib_multiple_scatter.py
gemseo_calibration/post/factory.py
gemseo_calibration/post/multiple_scatter.py
gemseo_calibration/post/data_versus_model/__init__.py
gemseo_calibration/post/data_versus_model/post.py
gemseo_calibration/post/data_versus_model/settings.py
gemseo_calibration/problems/__init__.py
gemseo_calibration/problems/signal/__init__.py
gemseo_calibration/problems/signal/oscillator.py
gemseo_calibration/signal/__init__.py
gemseo_calibration/signal/base_signal_generator.py
gemseo_calibration/signal/ode_signal_generator.py
gemseo_calibration/signal/signal_generator_discipline.py
gemseo_calibration-4.0.1.dist-info/licenses/LICENSE.txt
gemseo_calibration-4.0.1.dist-info/METADATA
gemseo_calibration-4.0.1.dist-info/WHEEL
gemseo_calibration-4.0.1.dist-info/entry_points.txt
gemseo_calibration-4.0.1.dist-info/top_level.txt
gemseo_calibration-4.0.1.dist-info/RECORD
